PyFunceble/ext/process_manager/__about__.py
PyFunceble/ext/process_manager/__init__.py
PyFunceble/ext/process_manager/core.py
PyFunceble/ext/process_manager/worker/__init__.py
PyFunceble/ext/process_manager/worker/core.py
examples/data_filter.py
pyfunceble_process_manager-1.0.11.dist-info/licenses/LICENSE
pyfunceble_process_manager-1.0.11.dist-info/METADATA
pyfunceble_process_manager-1.0.11.dist-info/WHEEL
pyfunceble_process_manager-1.0.11.dist-info/top_level.txt
pyfunceble_process_manager-1.0.11.dist-info/RECORD
