Metadata-Version: 2.4
Name: pyfunceble-process-manager
Version: 1.0.11
Summary: The process manager library for and from the PyFunceble project.
Home-page: https://github.com/PyFunceble/process-manager
Author: funilrys
Author-email: contact@funilrys.com
License: Apache 2.0
Project-URL: Source, https://github.com/PyFunceble/process-manager/tree/master
Project-URL: Tracker, https://github.com/PyFunceble/process-manager/issues
Keywords: PyFunceble,process-manager
Platform: any
Classifier: Environment :: Console
Classifier: Topic :: Internet
Classifier: Development Status :: 5 - Production/Stable
Classifier: Intended Audience :: Developers
Classifier: Programming Language :: Python
Classifier: Programming Language :: Python :: 3
Classifier: License :: OSI Approved
Requires-Python: >=3.8, <4
License-File: LICENSE
Requires-Dist: setuptools>=65.5.1
Provides-Extra: dev
Requires-Dist: flake8; extra == "dev"
Requires-Dist: bandit; extra == "dev"
Requires-Dist: isort; extra == "dev"
Requires-Dist: pylint; extra == "dev"
Requires-Dist: black; extra == "dev"
Provides-Extra: test
Requires-Dist: coverage; extra == "test"
Requires-Dist: pytest-cov; extra == "test"
Requires-Dist: pytest; extra == "test"
Provides-Extra: full
Requires-Dist: setuptools>=65.5.1; extra == "full"
Requires-Dist: pytest; extra == "full"
Requires-Dist: flake8; extra == "full"
Requires-Dist: bandit; extra == "full"
Requires-Dist: isort; extra == "full"
Requires-Dist: pylint; extra == "full"
Requires-Dist: coverage; extra == "full"
Requires-Dist: pytest-cov; extra == "full"
Requires-Dist: black; extra == "full"
Dynamic: author
Dynamic: author-email
Dynamic: classifier
Dynamic: description
Dynamic: description-content-type
Dynamic: home-page
Dynamic: keywords
Dynamic: license
Dynamic: license-file
Dynamic: platform
Dynamic: project-url
Dynamic: provides-extra
Dynamic: requires-dist
Dynamic: requires-python
Dynamic: summary
